<annotation>
	<folder>images</folder>
	<filename>angle_77.jpg</filename>
	<path>D:\!WORK\4. SMART\Work ~\1\Load Volume\Detection JKOTAK\tflite_maker_model\images\angle_77.jpg</path>
	<source>
		<database>Unknown</database>
	</source>
	<size>
		<width>2513</width>
		<height>4463</height>
		<depth>3</depth>
	</size>
	<segmented>0</segmented>
	<object>
		<name>kotak_2x1</name>
		<pose>Unspecified</pose>
		<truncated>0</truncated>
		<difficult>0</difficult>
		<bndbox>
			<xmin>1139</xmin>
			<ymin>1136</ymin>
			<xmax>1243</xmax>
			<ymax>1197</ymax>
		</bndbox>
	</object>
	<object>
		<name>kotak_2x1</name>
		<pose>Unspecified</pose>
		<truncated>0</truncated>
		<difficult>0</difficult>
		<bndbox>
			<xmin>1120</xmin>
			<ymin>2429</ymin>
			<xmax>1224</xmax>
			<ymax>2490</ymax>
		</bndbox>
	</object>
	<object>
		<name>kotak_2x1</name>
		<pose>Unspecified</pose>
		<truncated>0</truncated>
		<difficult>0</difficult>
		<bndbox>
			<xmin>1123</xmin>
			<ymin>2310</ymin>
			<xmax>1227</xmax>
			<ymax>2371</ymax>
		</bndbox>
	</object>
	<object>
		<name>kotak_2x1</name>
		<pose>Unspecified</pose>
		<truncated>0</truncated>
		<difficult>0</difficult>
		<bndbox>
			<xmin>1123</xmin>
			<ymin>2212</ymin>
			<xmax>1227</xmax>
			<ymax>2273</ymax>
		</bndbox>
	</object>
	<object>
		<name>kotak_2x1</name>
		<pose>Unspecified</pose>
		<truncated>0</truncated>
		<difficult>0</difficult>
		<bndbox>
			<xmin>1123</xmin>
			<ymin>1998</ymin>
			<xmax>1227</xmax>
			<ymax>2059</ymax>
		</bndbox>
	</object>
	<object>
		<name>kotak_2x1</name>
		<pose>Unspecified</pose>
		<truncated>0</truncated>
		<difficult>0</difficult>
		<bndbox>
			<xmin>1119</xmin>
			<ymin>2101</ymin>
			<xmax>1223</xmax>
			<ymax>2162</ymax>
		</bndbox>
	</object>
	<object>
		<name>kotak_2x1</name>
		<pose>Unspecified</pose>
		<truncated>0</truncated>
		<difficult>0</difficult>
		<bndbox>
			<xmin>1122</xmin>
			<ymin>1889</ymin>
			<xmax>1226</xmax>
			<ymax>1950</ymax>
		</bndbox>
	</object>
	<object>
		<name>kotak_2x1</name>
		<pose>Unspecified</pose>
		<truncated>0</truncated>
		<difficult>0</difficult>
		<bndbox>
			<xmin>1128</xmin>
			<ymin>1783</ymin>
			<xmax>1232</xmax>
			<ymax>1844</ymax>
		</bndbox>
	</object>
	<object>
		<name>kotak_2x1</name>
		<pose>Unspecified</pose>
		<truncated>0</truncated>
		<difficult>0</difficult>
		<bndbox>
			<xmin>1123</xmin>
			<ymin>1674</ymin>
			<xmax>1227</xmax>
			<ymax>1735</ymax>
		</bndbox>
	</object>
	<object>
		<name>kotak_2x1</name>
		<pose>Unspecified</pose>
		<truncated>0</truncated>
		<difficult>0</difficult>
		<bndbox>
			<xmin>1125</xmin>
			<ymin>1567</ymin>
			<xmax>1229</xmax>
			<ymax>1628</ymax>
		</bndbox>
	</object>
	<object>
		<name>kotak_2x1</name>
		<pose>Unspecified</pose>
		<truncated>0</truncated>
		<difficult>0</difficult>
		<bndbox>
			<xmin>1128</xmin>
			<ymin>1462</ymin>
			<xmax>1232</xmax>
			<ymax>1523</ymax>
		</bndbox>
	</object>
	<object>
		<name>kotak_2x1</name>
		<pose>Unspecified</pose>
		<truncated>0</truncated>
		<difficult>0</difficult>
		<bndbox>
			<xmin>1125</xmin>
			<ymin>1343</ymin>
			<xmax>1229</xmax>
			<ymax>1404</ymax>
		</bndbox>
	</object>
	<object>
		<name>kotak_2x1</name>
		<pose>Unspecified</pose>
		<truncated>0</truncated>
		<difficult>0</difficult>
		<bndbox>
			<xmin>1133</xmin>
			<ymin>1238</ymin>
			<xmax>1237</xmax>
			<ymax>1299</ymax>
		</bndbox>
	</object>
	<object>
		<name>kotak_2x1</name>
		<pose>Unspecified</pose>
		<truncated>0</truncated>
		<difficult>0</difficult>
		<bndbox>
			<xmin>1118</xmin>
			<ymin>2427</ymin>
			<xmax>1222</xmax>
			<ymax>2488</ymax>
		</bndbox>
	</object>
	<object>
		<name>kotak_2x1</name>
		<pose>Unspecified</pose>
		<truncated>0</truncated>
		<difficult>0</difficult>
		<bndbox>
			<xmin>1125</xmin>
			<ymin>3274</ymin>
			<xmax>1229</xmax>
			<ymax>3335</ymax>
		</bndbox>
	</object>
	<object>
		<name>kotak_2x1</name>
		<pose>Unspecified</pose>
		<truncated>0</truncated>
		<difficult>0</difficult>
		<bndbox>
			<xmin>1122</xmin>
			<ymin>3068</ymin>
			<xmax>1226</xmax>
			<ymax>3129</ymax>
		</bndbox>
	</object>
	<object>
		<name>kotak_2x1</name>
		<pose>Unspecified</pose>
		<truncated>0</truncated>
		<difficult>0</difficult>
		<bndbox>
			<xmin>1120</xmin>
			<ymin>2958</ymin>
			<xmax>1224</xmax>
			<ymax>3019</ymax>
		</bndbox>
	</object>
	<object>
		<name>kotak_2x1</name>
		<pose>Unspecified</pose>
		<truncated>0</truncated>
		<difficult>0</difficult>
		<bndbox>
			<xmin>1128</xmin>
			<ymin>2744</ymin>
			<xmax>1232</xmax>
			<ymax>2805</ymax>
		</bndbox>
	</object>
	<object>
		<name>kotak_2x1</name>
		<pose>Unspecified</pose>
		<truncated>0</truncated>
		<difficult>0</difficult>
		<bndbox>
			<xmin>1127</xmin>
			<ymin>2642</ymin>
			<xmax>1231</xmax>
			<ymax>2703</ymax>
		</bndbox>
	</object>
	<object>
		<name>kotak_2x1</name>
		<pose>Unspecified</pose>
		<truncated>0</truncated>
		<difficult>0</difficult>
		<bndbox>
			<xmin>1123</xmin>
			<ymin>2536</ymin>
			<xmax>1227</xmax>
			<ymax>2597</ymax>
		</bndbox>
	</object>
	<object>
		<name>kotak_2x1</name>
		<pose>Unspecified</pose>
		<truncated>0</truncated>
		<difficult>0</difficult>
		<bndbox>
			<xmin>1122</xmin>
			<ymin>3490</ymin>
			<xmax>1226</xmax>
			<ymax>3551</ymax>
		</bndbox>
	</object>
	<object>
		<name>kotak_2x1</name>
		<pose>Unspecified</pose>
		<truncated>0</truncated>
		<difficult>0</difficult>
		<bndbox>
			<xmin>1124</xmin>
			<ymin>3378</ymin>
			<xmax>1228</xmax>
			<ymax>3439</ymax>
		</bndbox>
	</object>
	<object>
		<name>kotak_2x1</name>
		<pose>Unspecified</pose>
		<truncated>0</truncated>
		<difficult>0</difficult>
		<bndbox>
			<xmin>1122</xmin>
			<ymin>3174</ymin>
			<xmax>1226</xmax>
			<ymax>3235</ymax>
		</bndbox>
	</object>
	<object>
		<name>kotak_2x1</name>
		<pose>Unspecified</pose>
		<truncated>0</truncated>
		<difficult>0</difficult>
		<bndbox>
			<xmin>1125</xmin>
			<ymin>2854</ymin>
			<xmax>1229</xmax>
			<ymax>2915</ymax>
		</bndbox>
	</object>
</annotation>
