<annotation>
	<folder>odometer_model_jkotak2x1</folder>
	<filename>ditengah mal 22.jpg</filename>
	<path>D:\!WORK\4. SMART\Work ~\1\Load Volume\odometer_model_jkotak2x1\ditengah mal 22.jpg</path>
	<source>
		<database>Unknown</database>
	</source>
	<size>
		<width>4270</width>
		<height>2405</height>
		<depth>3</depth>
	</size>
	<segmented>0</segmented>
	<object>
		<name>kotak_2x1</name>
		<pose>Unspecified</pose>
		<truncated>0</truncated>
		<difficult>0</difficult>
		<bndbox>
			<xmin>2054</xmin>
			<ymin>1099</ymin>
			<xmax>2381</xmax>
			<ymax>1238</ymax>
		</bndbox>
	</object>
	<object>
		<name>kotak_2x1</name>
		<pose>Unspecified</pose>
		<truncated>0</truncated>
		<difficult>0</difficult>
		<bndbox>
			<xmin>2058</xmin>
			<ymin>1389</ymin>
			<xmax>2363</xmax>
			<ymax>1541</ymax>
		</bndbox>
	</object>
	<object>
		<name>kotak_2x1</name>
		<pose>Unspecified</pose>
		<truncated>0</truncated>
		<difficult>0</difficult>
		<bndbox>
			<xmin>2055</xmin>
			<ymin>1689</ymin>
			<xmax>2357</xmax>
			<ymax>1846</ymax>
		</bndbox>
	</object>
	<object>
		<name>kotak_2x1</name>
		<pose>Unspecified</pose>
		<truncated>0</truncated>
		<difficult>0</difficult>
		<bndbox>
			<xmin>2052</xmin>
			<ymin>1995</ymin>
			<xmax>2363</xmax>
			<ymax>2155</ymax>
		</bndbox>
	</object>
</annotation>
